{
  "sections": {
    "image_banner": {
      "type": "image-banner",
      "blocks": {
        "heading": {
          "type": "heading",
          "settings": {
            "heading": "Tap into Quality: Elevate Your Brew with KegCollars.net",
            "heading_size": "h1"
          }
        },
        "text": {
          "type": "text",
          "settings": {
            "text": "KegCollars.net has everything you need for to bring a fresh branded look to your Keg Collars, Keg Wraps, Coasters, Growler Tags, and more!",
            "text_style": "subtitle"
          }
        },
        "button": {
          "type": "buttons",
          "settings": {
            "button_label_1": "Shop all",
            "button_link_1": "shopify:\/\/collections\/all",
            "button_style_secondary_1": false,
            "button_label_2": "Design Your Own!",
            "button_link_2": "shopify:\/\/collections\/template-keg-collars",
            "button_style_secondary_2": false
          }
        }
      },
      "block_order": [
        "heading",
        "text",
        "button"
      ],
      "settings": {
        "image": "shopify:\/\/shop_images\/Coffee-Cartel.png",
        "image_2": "shopify:\/\/shop_images\/Custom_Design_Keg_Collar_Studio.png",
        "image_overlay_opacity": 60,
        "image_height": "large",
        "desktop_content_position": "bottom-center",
        "show_text_box": false,
        "desktop_content_alignment": "center",
        "color_scheme": "inverse",
        "image_behavior": "none",
        "mobile_content_alignment": "center",
        "stack_images_on_mobile": false,
        "show_text_below": false
      }
    },
    "9eb9690d-003e-48a6-8d25-17cc5e97f5f8": {
      "type": "collection-list",
      "blocks": {
        "template--20079615312182__9eb9690d-003e-48a6-8d25-17cc5e97f5f8-featured_collection-1": {
          "type": "featured_collection",
          "settings": {
            "collection": "custom-design-keg-collars"
          }
        },
        "template--20079615312182__9eb9690d-003e-48a6-8d25-17cc5e97f5f8-featured_collection-2": {
          "type": "featured_collection",
          "settings": {
            "collection": "template-keg-collars"
          }
        },
        "template--20079615312182__9eb9690d-003e-48a6-8d25-17cc5e97f5f8-featured_collection-3": {
          "type": "featured_collection",
          "settings": {
            "collection": "stock-keg-collars"
          }
        }
      },
      "block_order": [
        "template--20079615312182__9eb9690d-003e-48a6-8d25-17cc5e97f5f8-featured_collection-1",
        "template--20079615312182__9eb9690d-003e-48a6-8d25-17cc5e97f5f8-featured_collection-2",
        "template--20079615312182__9eb9690d-003e-48a6-8d25-17cc5e97f5f8-featured_collection-3"
      ],
      "settings": {
        "title": "3 Easy Ways to Order Keg Collars",
        "heading_size": "h1",
        "image_ratio": "square",
        "columns_desktop": 3,
        "color_scheme": "",
        "show_view_all": false,
        "columns_mobile": "1",
        "swipe_on_mobile": false,
        "padding_top": 36,
        "padding_bottom": 36
      }
    },
    "rich_text": {
      "type": "rich-text",
      "blocks": {
        "heading": {
          "type": "heading",
          "settings": {
            "heading": "Need help designing your keg collar?",
            "heading_size": "h1"
          }
        },
        "text": {
          "type": "text",
          "settings": {
            "text": "<p>Browse our collection of easy to complete do-it-yourself (DIY) keg collar templates. Simply upload your<br\/>logo and fill in the information fields for a personalized keg collar in matter of minutes.<br\/><\/p>"
          }
        }
      },
      "block_order": [
        "heading",
        "text"
      ],
      "settings": {
        "desktop_content_position": "center",
        "content_alignment": "center",
        "color_scheme": "background-1",
        "full_width": true,
        "padding_top": 48,
        "padding_bottom": 48
      }
    },
    "collage": {
      "type": "collage",
      "blocks": {
        "collection-0": {
          "type": "collection",
          "settings": {
            "collection": "custom-design-keg-collars"
          }
        },
        "collection-1": {
          "type": "collection",
          "settings": {
            "collection": "stock-keg-collars"
          }
        },
        "5183b4c7-ea72-4f0e-b21b-2ae941383857": {
          "type": "collection",
          "settings": {
            "collection": "template-keg-collars"
          }
        }
      },
      "block_order": [
        "collection-0",
        "collection-1",
        "5183b4c7-ea72-4f0e-b21b-2ae941383857"
      ],
      "disabled": true,
      "settings": {
        "heading": "Find the Perfect Keg Collar for Every Requirement",
        "heading_size": "h2",
        "desktop_layout": "right",
        "mobile_layout": "collage",
        "card_styles": "none",
        "color_scheme": "background-2",
        "padding_top": 48,
        "padding_bottom": 48
      }
    },
    "9c5e0290-9f6c-4655-bc5e-1f5d781bf522": {
      "type": "swiper-product-list",
      "settings": {
        "title": "Template Keg Collars",
        "heading_size": "h2",
        "description": "<p>{{ shop.brand.short_description }}<\/p>",
        "show_description": true,
        "description_style": "subtitle",
        "product_collection": "template-keg-collars",
        "num_products": 10,
        "color_scheme": "background-2",
        "full_width": false,
        "image_ratio": "adapt",
        "image_shape": "default",
        "show_secondary_image": true,
        "slides_per_view_desktop": "4",
        "space_between": 16,
        "padding_top": 48,
        "padding_bottom": 48
      }
    },
    "68684dd1-411b-4c26-a14f-a07231baa480": {
      "type": "rich-text",
      "blocks": {
        "template--20079615312182__68684dd1-411b-4c26-a14f-a07231baa480-heading-1": {
          "type": "heading",
          "settings": {
            "heading": "Need Items Quickly?",
            "heading_size": "h1"
          }
        },
        "template--20079615312182__68684dd1-411b-4c26-a14f-a07231baa480-text-1": {
          "type": "text",
          "settings": {
            "text": "<p>Visit our pre-printed stock shop with various ready-to-ship keg collars, keg caps, coasters and required government warning labels.<\/p>"
          }
        },
        "template--20079615312182__68684dd1-411b-4c26-a14f-a07231baa480-button-1": {
          "type": "button",
          "settings": {
            "button_label": "Shop Now",
            "button_link": "shopify:\/\/collections\/stock-keg-collars",
            "button_style_secondary": false,
            "button_label_2": "",
            "button_link_2": "",
            "button_style_secondary_2": false
          }
        }
      },
      "block_order": [
        "template--20079615312182__68684dd1-411b-4c26-a14f-a07231baa480-heading-1",
        "template--20079615312182__68684dd1-411b-4c26-a14f-a07231baa480-text-1",
        "template--20079615312182__68684dd1-411b-4c26-a14f-a07231baa480-button-1"
      ],
      "settings": {
        "desktop_content_position": "center",
        "content_alignment": "center",
        "color_scheme": "",
        "full_width": true,
        "padding_top": 40,
        "padding_bottom": 52
      }
    },
    "featured_collection": {
      "type": "featured-collection",
      "settings": {
        "title": "Featured Pre-Printed Stock Items",
        "heading_size": "h2",
        "description": "<p>All items are printed and ready to ship!<\/p>",
        "show_description": false,
        "description_style": "body",
        "collection": "stock-keg-collars",
        "products_to_show": 8,
        "columns_desktop": 4,
        "full_width": false,
        "show_view_all": false,
        "view_all_style": "solid",
        "enable_desktop_slider": false,
        "color_scheme": "background-1",
        "image_ratio": "square",
        "image_shape": "default",
        "show_secondary_image": true,
        "show_vendor": false,
        "show_rating": false,
        "enable_quick_add": false,
        "columns_mobile": "2",
        "swipe_on_mobile": false,
        "padding_top": 28,
        "padding_bottom": 36
      }
    },
    "video": {
      "type": "video",
      "disabled": true,
      "settings": {
        "heading": "",
        "heading_size": "h1",
        "enable_video_looping": false,
        "video_url": "https:\/\/www.youtube.com\/watch?v=_9VUPq3SxOc",
        "description": "",
        "full_width": false,
        "color_scheme": "background-1",
        "padding_top": 36,
        "padding_bottom": 36
      }
    },
    "multicolumn": {
      "type": "multicolumn",
      "blocks": {
        "column1": {
          "type": "column",
          "settings": {
            "title": "Column",
            "text": "<p>Pair text with an image to focus on your chosen product, collection, or blog post. Add details on availability, style, or even provide a review.<\/p>",
            "link_label": "",
            "link": ""
          }
        },
        "column2": {
          "type": "column",
          "settings": {
            "title": "Column",
            "text": "<p>Pair text with an image to focus on your chosen product, collection, or blog post. Add details on availability, style, or even provide a review.<\/p>",
            "link_label": "",
            "link": ""
          }
        },
        "column3": {
          "type": "column",
          "settings": {
            "title": "Column",
            "text": "<p>Pair text with an image to focus on your chosen product, collection, or blog post. Add details on availability, style, or even provide a review.<\/p>",
            "link_label": "",
            "link": ""
          }
        },
        "c9ae2c70-aa1e-4f47-8e69-de58ee88ed01": {
          "type": "column",
          "settings": {
            "title": "Column",
            "text": "<p>Pair text with an image to focus on your chosen product, collection, or blog post. Add details on availability, style, or even provide a review.<\/p>",
            "link_label": "",
            "link": ""
          }
        }
      },
      "block_order": [
        "column1",
        "column2",
        "column3",
        "c9ae2c70-aa1e-4f47-8e69-de58ee88ed01"
      ],
      "disabled": true,
      "settings": {
        "title": "",
        "heading_size": "h1",
        "image_width": "third",
        "image_ratio": "adapt",
        "columns_desktop": 3,
        "column_alignment": "center",
        "background_style": "none",
        "button_label": "",
        "button_link": "",
        "color_scheme": "background-1",
        "columns_mobile": "1",
        "swipe_on_mobile": false,
        "padding_top": 36,
        "padding_bottom": 36
      }
    },
    "47f6c410-1eea-4bc6-bfec-51abae3bd91e": {
      "type": "featured-product",
      "blocks": {
        "template--20079615312182__47f6c410-1eea-4bc6-bfec-51abae3bd91e-text-1": {
          "type": "text",
          "settings": {
            "text": "{{ section.settings.product.vendor }}",
            "text_style": "uppercase"
          }
        },
        "template--20079615312182__47f6c410-1eea-4bc6-bfec-51abae3bd91e-title-1": {
          "type": "title",
          "settings": {
            "heading_size": "h1"
          }
        },
        "template--20079615312182__47f6c410-1eea-4bc6-bfec-51abae3bd91e-price-1": {
          "type": "price",
          "settings": {
          }
        },
        "template--20079615312182__47f6c410-1eea-4bc6-bfec-51abae3bd91e-variant_picker-1": {
          "type": "variant_picker",
          "settings": {
            "picker_type": "button"
          }
        },
        "template--20079615312182__47f6c410-1eea-4bc6-bfec-51abae3bd91e-quantity_selector-1": {
          "type": "quantity_selector",
          "settings": {
          }
        },
        "template--20079615312182__47f6c410-1eea-4bc6-bfec-51abae3bd91e-buy_buttons-1": {
          "type": "buy_buttons",
          "settings": {
            "show_dynamic_checkout": true,
            "show_gift_card_recipient": true
          }
        },
        "template--20079615312182__47f6c410-1eea-4bc6-bfec-51abae3bd91e-share-1": {
          "type": "share",
          "settings": {
            "share_label": "Share"
          }
        }
      },
      "block_order": [
        "template--20079615312182__47f6c410-1eea-4bc6-bfec-51abae3bd91e-text-1",
        "template--20079615312182__47f6c410-1eea-4bc6-bfec-51abae3bd91e-title-1",
        "template--20079615312182__47f6c410-1eea-4bc6-bfec-51abae3bd91e-price-1",
        "template--20079615312182__47f6c410-1eea-4bc6-bfec-51abae3bd91e-variant_picker-1",
        "template--20079615312182__47f6c410-1eea-4bc6-bfec-51abae3bd91e-quantity_selector-1",
        "template--20079615312182__47f6c410-1eea-4bc6-bfec-51abae3bd91e-buy_buttons-1",
        "template--20079615312182__47f6c410-1eea-4bc6-bfec-51abae3bd91e-share-1"
      ],
      "settings": {
        "product": "black-stripe-keg-collar",
        "color_scheme": "",
        "secondary_background": false,
        "media_size": "medium",
        "constrain_to_viewport": true,
        "media_fit": "contain",
        "media_position": "left",
        "image_zoom": "lightbox",
        "hide_variants": false,
        "enable_video_looping": false,
        "padding_top": 36,
        "padding_bottom": 36
      }
    },
    "b4d860ee-52a6-46bc-83ee-eef116d64930": {
      "type": "multicolumn",
      "blocks": {
        "template--20079615312182__b4d860ee-52a6-46bc-83ee-eef116d64930-column-1": {
          "type": "column",
          "settings": {
            "title": "",
            "text": "<p>Our favorite thing about using<br\/>kegcollars.net is the ease of<br\/>ordering, the superior customer<br\/>service, and most importantly, the quality of the product.<br\/><\/p><p>- Upslope Brewing<br\/><\/p>",
            "link_label": "",
            "link": ""
          }
        },
        "template--20079615312182__b4d860ee-52a6-46bc-83ee-eef116d64930-column-2": {
          "type": "column",
          "settings": {
            "title": "",
            "text": "<p>We found out about keg collars.net from seeing the quality of work they’d done for our friends and their breweries. Keg Collars.net makes it quick, easy and effortless to order.<br\/><\/p><p>-Goodlife Brewing<br\/><\/p>",
            "link_label": "",
            "link": ""
          }
        },
        "template--20079615312182__b4d860ee-52a6-46bc-83ee-eef116d64930-column-3": {
          "type": "column",
          "settings": {
            "title": "",
            "text": "<p>We love how simple it is to customize the keg collars to fit our needs. The ability to track our orders as it progresses in production is also really neat.<br\/><\/p><p>-Cartel Coffee Lab<\/p>",
            "link_label": "",
            "link": ""
          }
        }
      },
      "block_order": [
        "template--20079615312182__b4d860ee-52a6-46bc-83ee-eef116d64930-column-1",
        "template--20079615312182__b4d860ee-52a6-46bc-83ee-eef116d64930-column-2",
        "template--20079615312182__b4d860ee-52a6-46bc-83ee-eef116d64930-column-3"
      ],
      "settings": {
        "title": "Reviews",
        "heading_size": "h1",
        "image_width": "full",
        "image_ratio": "adapt",
        "columns_desktop": 3,
        "column_alignment": "center",
        "background_style": "primary",
        "button_label": "",
        "button_link": "",
        "color_scheme": "",
        "columns_mobile": "1",
        "swipe_on_mobile": false,
        "padding_top": 36,
        "padding_bottom": 36
      }
    }
  },
  "order": [
    "image_banner",
    "9eb9690d-003e-48a6-8d25-17cc5e97f5f8",
    "rich_text",
    "collage",
    "9c5e0290-9f6c-4655-bc5e-1f5d781bf522",
    "68684dd1-411b-4c26-a14f-a07231baa480",
    "featured_collection",
    "video",
    "multicolumn",
    "47f6c410-1eea-4bc6-bfec-51abae3bd91e",
    "b4d860ee-52a6-46bc-83ee-eef116d64930"
  ]
}
